aoh/__init__.py
aoh/aohcalc.py
aoh/cleaning.py
aoh/habitat_process.py
aoh/py.typed
aoh/_internal/__init__.py
aoh/_internal/aoh_binary.py
aoh/_internal/aoh_fractional.py
aoh/_internal/speciesinfo.py
aoh/summaries/__init__.py
aoh/summaries/endemism.py
aoh/summaries/species_richness.py
aoh/validation/__init__.py
aoh/validation/collate_data.py
aoh/validation/fetch_gbif_data.py
aoh/validation/validate_map_prevalence.py
aoh/validation/validate_occurences.py
aoh-2.0.4.dist-info/licenses/LICENSE
aoh-2.0.4.dist-info/METADATA
aoh-2.0.4.dist-info/WHEEL
aoh-2.0.4.dist-info/entry_points.txt
aoh-2.0.4.dist-info/top_level.txt
aoh-2.0.4.dist-info/RECORD
