Metadata-Version: 2.4
Name: aoh
Version: 2.0.4
Summary: A library for calculating Area of Habitat for species distribution mapping
Author-email: Michael Dales <mwd24@cam.ac.uk>
License-Expression: ISC
Project-URL: Homepage, https://github.com/quantifyearth/aoh-calculator
Project-URL: Repository, https://github.com/quantifyearth/aoh-calculator
Project-URL: Issues, https://github.com/quantifyearth/aoh-calculator/issues
Keywords: gis,species,habitat,biodiversity,ecology
Classifier: Development Status :: 5 - Production/Stable
Classifier: Intended Audience :: Science/Research
Classifier: Programming Language :: Python :: 3
Classifier: Programming Language :: Python :: 3.10
Classifier: Programming Language :: Python :: 3.11
Classifier: Programming Language :: Python :: 3.12
Classifier: Topic :: Scientific/Engineering :: GIS
Requires-Python: >=3.10
License-File: LICENSE
Requires-Dist: alive-progress
Requires-Dist: numpy<3.0,>=1.24
Requires-Dist: geopandas<2.0,>=1.0
Requires-Dist: psutil
Requires-Dist: pyproj<4.0,>=3.4
Requires-Dist: scikit-image<1.0,>=0.20
Requires-Dist: yirgacheffe<2.0,>=1.12.2
Requires-Dist: zenodo_search
Requires-Dist: pandas<3.0,>=2.0
Requires-Dist: gdal[numpy]<3.13,>=3.8
Requires-Dist: tomli
Provides-Extra: validation
Requires-Dist: pymer4==0.8.2; extra == "validation"
Requires-Dist: rpy2; extra == "validation"
Requires-Dist: joblib; extra == "validation"
Requires-Dist: seaborn; extra == "validation"
Requires-Dist: matplotlib; extra == "validation"
Requires-Dist: great_tables; extra == "validation"
Requires-Dist: scikit-learn; extra == "validation"
Requires-Dist: formulae; extra == "validation"
Requires-Dist: pygbif==0.6.6; extra == "validation"
Provides-Extra: dev
Requires-Dist: pylint; extra == "dev"
Requires-Dist: mypy; extra == "dev"
Requires-Dist: pytest; extra == "dev"
Requires-Dist: types-geopandas; extra == "dev"
Requires-Dist: types-psutil; extra == "dev"
Requires-Dist: types-requests; extra == "dev"
Requires-Dist: types-shapely; extra == "dev"
Requires-Dist: pandas-stubs; extra == "dev"
Requires-Dist: geojson; extra == "dev"
Requires-Dist: pytest-cov; extra == "dev"
Requires-Dist: build; extra == "dev"
Requires-Dist: twine; extra == "dev"
Dynamic: license-file
